{
    "info": {
        "name": "accident",
        "description": "",
        "url": ""
    },
    "video": {
        "video_name": "bb_1_170803_bike_212_21546",
        "video_date": "170803",
        "filming_way": "bb",
        "video_point_of_view": 1,
        "accident_negligence_rateA": 60,
        "accident_negligence_rateB": 40,
        "accident_object": 3,
        "accident_place": 0,
        "accident_place_feature": 52,
        "vehicle_a_progress_info": 158,
        "vehicle_b_progress_info": 159,
        "damage_location": "",
        "related_laws": "",
        "violation_of_law": "",
        "additional_elements": "",
        "violation_factor": "",
        "weather": "",
        "traffic_accident_type": 380
    }
}