{
	"info": {
		"name": "accident",
		"description": "",
		"url": ""
	},
	"video": {
		"video_name": "cc_3_180629_two-wheeled-vehicle_120_173",
		"video_date": "180629",
		"filming_way": "cc",
		"video_point_of_view": 3,
		"accident_negligence_rateA": 60,
		"accident_negligence_rateB": 40,
		"accident_object": 2,
		"accident_place": 1,
		"accident_place_feature": 10,
		"vehicle_a_progress_info": 106,
		"vehicle_b_progress_info": 6,
		"damage_location": "",
		"related_laws": "",
		"violation_of_law": "",
		"additional_elements": "",
		"violation_factor": "",
		"weather": "",
		"traffic_accident_type": 231
	}
}